MANIFEST.in
README.rst
setup.py
src/django_lime.egg-info/PKG-INFO
src/django_lime.egg-info/SOURCES.txt
src/django_lime.egg-info/dependency_links.txt
src/django_lime.egg-info/requires.txt
src/django_lime.egg-info/top_level.txt
src/lime/__init__.py
src/lime/conf.py
src/lime/defaults.py
src/lime/helpers.py
src/lime/settings.py
src/lime/templates/lime/base.html
src/lime/templates/lime/base.txt